magnum_capi_helm/__init__.py
magnum_capi_helm/conf.py
magnum_capi_helm/driver.py
magnum_capi_helm/driver_utils.py
magnum_capi_helm/helm.py
magnum_capi_helm/kubernetes.py
magnum_capi_helm/common/README.rst
magnum_capi_helm/common/__init__.py
magnum_capi_helm/common/app_creds.py
magnum_capi_helm/common/ca_certificates.py
magnum_capi_helm/common/capi_monitor.py
magnum_capi_helm/tests/__init__.py
magnum_capi_helm/tests/base.py
magnum_capi_helm/tests/test_driver.py
magnum_capi_helm/tests/test_helm.py
magnum_capi_helm/tests/test_kubernetes.py
magnum_capi_helm/tests/test_magnum_capi_helm.py
magnum_capi_helm/tests/common/__init__.py
magnum_capi_helm/tests/common/test_app_creds.py
magnum_capi_helm/tests/common/test_ca_certificates.py
magnum_capi_helm/tests/common/test_capi_monitor.py
magnum_capi_helm-1.3.0.dist-info/AUTHORS
magnum_capi_helm-1.3.0.dist-info/LICENSE
magnum_capi_helm-1.3.0.dist-info/METADATA
magnum_capi_helm-1.3.0.dist-info/WHEEL
magnum_capi_helm-1.3.0.dist-info/entry_points.txt
magnum_capi_helm-1.3.0.dist-info/pbr.json
magnum_capi_helm-1.3.0.dist-info/top_level.txt
magnum_capi_helm-1.3.0.dist-info/RECORD
