Metadata-Version: 2.1
Name: magnum-capi-helm
Version: 1.3.0
Summary: OpenStack Magnum driver using helm to create k8s clusters with Cluster API.
Home-page: https://www.openstack.org/
Author: OpenStack
Author-email: openstack-discuss@lists.openstack.org
Classifier: Environment :: OpenStack
Classifier: Intended Audience :: Information Technology
Classifier: Intended Audience :: System Administrators
Classifier: License :: OSI Approved :: Apache Software License
Classifier: Operating System :: POSIX :: Linux
Classifier: Programming Language :: Python
Classifier: Programming Language :: Python :: 3
Classifier: Programming Language :: Python :: 3.7
Classifier: Programming Language :: Python :: 3.8
Classifier: Programming Language :: Python :: 3.9
Classifier: Programming Language :: Python :: 3 :: Only
Classifier: Programming Language :: Python :: Implementation :: CPython
Requires-Python: >=3.6
License-File: LICENSE
License-File: AUTHORS
Requires-Dist: pbr >=2.0
Requires-Dist: oslo-log
Requires-Dist: oslo-utils
Requires-Dist: magnum
